coomify.py
coomify-1.1.5.dist-info/METADATA
coomify-1.1.5.dist-info/WHEEL
coomify-1.1.5.dist-info/entry_points.txt
coomify-1.1.5.dist-info/top_level.txt
coomify-1.1.5.dist-info/RECORD
